create_wheel/__init__.py
create_wheel/__main__.py
create_wheel/create_wheel.py
create_wheel/setup.py
create_wheel-1.1.dist-info/METADATA
create_wheel-1.1.dist-info/WHEEL
create_wheel-1.1.dist-info/entry_points.txt
create_wheel-1.1.dist-info/top_level.txt
create_wheel-1.1.dist-info/RECORD
