Metadata-Version: 2.1
Name: create-wheel
Version: 1.1
Summary: Package to create wheel file
Author: Pankaj Kalal
Author-email: pankajgkalal@gmail.com
Classifier: Programming Language :: Python :: 3
Classifier: License :: OSI Approved :: MIT License
Classifier: Operating System :: OS Independent
Requires-Python: >=3.7
Requires-Dist: pipreqs
Requires-Dist: importlib-resources
